MANIFEST.in
README.rst
requirements.txt
setup.cfg
setup.py
faker_cloud/__init__.py
faker_cloud/cloud.py
faker_cloud/tests.py
faker_cloud.egg-info/PKG-INFO
faker_cloud.egg-info/SOURCES.txt
faker_cloud.egg-info/dependency_links.txt
faker_cloud.egg-info/requires.txt
faker_cloud.egg-info/top_level.txt
faker_cloud/amazon_web_services/__init__.py
faker_cloud/amazon_web_services/tests.py
faker_cloud/upcloud/__init__.py
faker_cloud/upcloud/tests.py